mailerlite_wrapper/__init__.py
mailerlite_wrapper/wrapper.py
mailerlite_wrapper-0.1.0.dist-info/METADATA
mailerlite_wrapper-0.1.0.dist-info/WHEEL
mailerlite_wrapper-0.1.0.dist-info/licenses/LICENSE
mailerlite_wrapper-0.1.0.dist-info/RECORD
