Metadata-Version: 2.4
Name: mailerlite_wrapper
Version: 0.1.0
Summary: A simple, class-based Python wrapper for the MailerLite API.
Author-email: Sash Kap <sashkap2521@gmail.com>
License-File: LICENSE
Classifier: Intended Audience :: Developers
Classifier: License :: Public Domain
Classifier: Operating System :: OS Independent
Classifier: Programming Language :: Python :: 3
Classifier: Topic :: Communications :: Email
Requires-Python: >=3.8
Requires-Dist: mailerlite>=0.1.10
